panderaext/__init__.py
panderaext/checks.py
panderaext/schema_helper.py
panderaext/serializable_check_types.py
panderaext-0.1.1.dist-info/LICENSE
panderaext-0.1.1.dist-info/METADATA
panderaext-0.1.1.dist-info/WHEEL
panderaext-0.1.1.dist-info/RECORD
